shiertier_huggingface/__init__.py
shiertier_huggingface/huggingface.py
shiertier_huggingface-0.1.7.dist-info/LICENSE
shiertier_huggingface-0.1.7.dist-info/METADATA
shiertier_huggingface-0.1.7.dist-info/WHEEL
shiertier_huggingface-0.1.7.dist-info/top_level.txt
shiertier_huggingface-0.1.7.dist-info/RECORD
