Metadata-Version: 2.1
Name: shiertier_huggingface
Version: 0.1.7
Summary: A simple huggingface client for Python.
Author-email: shiertier <junjie.text@gmail.com>
License: MIT License
Classifier: Development Status :: 3 - Alpha
Classifier: Intended Audience :: Developers
Classifier: License :: OSI Approved :: MIT License
Classifier: Programming Language :: Python :: 3
Classifier: Programming Language :: Python :: 3.7
Classifier: Programming Language :: Python :: 3.8
Classifier: Programming Language :: Python :: 3.9
Classifier: Programming Language :: Python :: 3.10
Classifier: Programming Language :: Python :: 3.11
Classifier: Programming Language :: Python :: 3.12
Requires-Python: >=3.7
License-File: LICENSE
Requires-Dist: huggingface-hub
Requires-Dist: shiertier-tar
Requires-Dist: shiertier-logger
